mitz_datagen/__init__.py
mitz_datagen/main.py
mitz_datagen-0.0.1.dist-info/LICENSE
mitz_datagen-0.0.1.dist-info/METADATA
mitz_datagen-0.0.1.dist-info/WHEEL
mitz_datagen-0.0.1.dist-info/top_level.txt
mitz_datagen-0.0.1.dist-info/RECORD
